MANIFEST.in
setup.py
version.py
mang/__init__.py
mang/cost.py
mang/cpu_conv.py
mang/feedforwardnetwork.py
mang/graph.py
mang/measure.py
mang/noise.py
mang/preprocessing.py
mang/util.py
mang/visualization.py
mang.egg-info/PKG-INFO
mang.egg-info/SOURCES.txt
mang.egg-info/dependency_links.txt
mang.egg-info/not-zip-safe
mang.egg-info/top_level.txt
mang/cudamat/INSTALL.txt
mang/cudamat/Makefile
mang/cudamat/README.txt
mang/cudamat/__init__.py
mang/cudamat/cudamat.cu
mang/cudamat/cudamat.cuh
mang/cudamat/cudamat.py
mang/cudamat/cudamat_conv.cu
mang/cudamat/cudamat_conv.cuh
mang/cudamat/cudamat_conv.py
mang/cudamat/cudamat_conv_kernels.cu
mang/cudamat/cudamat_conv_kernels.cuh
mang/cudamat/cudamat_kernels.cu
mang/cudamat/cudamat_kernels.cuh
mang/cudamat/learn.cu
mang/cudamat/learn.py
mang/cudamat/learn_kernels.cu
mang/cudamat/learn_kernels.cuh
mang/cudamat/libcudamat.so
mang/cudamat/libcudamat_conv.so
mang/cudamat/rnd_multipliers_32bit.txt
mang/cudamat/test_cudamat.py
mang/cudamat/test_learn.py
mang/edge/__init__.py
mang/edge/convolutional_edge.py
mang/edge/deconvolutional_edge.py
mang/edge/edge.py
mang/edge/edge_ref.py
mang/edge/max_pooling_edge.py
mang/node/__init__.py
mang/node/functions.py
mang/node/logistic_node.py
mang/node/node.py
mang/node/relu_node.py
mang/node/response_normalization_node.py
mang/node/softmax_node.py
mang/node/tanh_node.py
test/test.py