Metadata-Version: 1.0
Name: mang
Version: 0.1.3-1-g8a5aa39
Summary: Another neural network library for python based on cudamat
Home-page: http://github.com/e0en/mang
Author: Yoonseop Kang
Author-email: e0engoon@gmail.com
License: UNKNOWN
Keywords: neural network,artificial intelligence,machine learning
Platform: UNKNOWN
